auto_api_tester/__init__.py
auto_api_tester/main.py
auto_api_tester/utils.py
auto_api_tester-1.0.2.dist-info/METADATA
auto_api_tester-1.0.2.dist-info/WHEEL
auto_api_tester-1.0.2.dist-info/licenses/LICENSE
auto_api_tester-1.0.2.dist-info/RECORD
