Metadata-Version: 2.1
Name: auto-api-tester
Version: 1.0.2
Summary: Tool to test RESTful APIs with built in and user input functions
Project-URL: Homepage, https://github.com/jkgriffiths93/auto_api_tester
Author-email: Jeff Griffiths <jkgriffiths93@gmail.com>
License-File: LICENSE
Classifier: License :: OSI Approved :: MIT License
Classifier: Operating System :: OS Independent
Classifier: Programming Language :: Python :: 3
Requires-Python: >=3.7
Requires-Dist: ipython>=8.10.0
Requires-Dist: requests>=2.28.1
Requires-Dist: timer-bar>=1.0.1
